[
    {
      "id": 1,
      "name": "All Product",
      "category": "All-product"
    },
    {
      "id": 2,
      "name": "Laptops",
      "category": "Laptop"
    },
    {
      "id": 3,
      "name": "Phones",
      "category": "Phone"
    },
    {
      "id": 4,
      "name": "Accessories",
      "category": "Accessories"
    },
    {
      "id": 5,
      "name": "Smart Watches",
      "category": "Smart Watches"
    },
    {
      "id": 6,
      "name": "MacBook",
      "category": "Macbook"
    },
    {
      "id": 7,
      "name": "Iphone",
      "category": "Iphone"
    }
  ]
  